<?xml version="1.0" encoding="UTF-8"?>
<Zone AttemptSKUConsolidation="" BuildingNumber="" CheckDigit=""
    ConfirmLocnEmptyAfterPick="" Description="" ForceLocnScanOnVisit=""
    IsActiveZone="" LocationsPerItem="" MaximumRecords=""
    MixCountryOfOrigin="" MixEnterprise="" MixFifo=""
    MixInventoryStatus="" MixInventoryTag="" MixProductClass=""
    MixReceiptNo="" MixSKU="" MixSegment="" MixShipByDate="" Node=""
    PrimaryBulkZoneId="" PutOnVarianceHold="" TrackCaseLPN=""
    TrackInventory="" TrackPalletLPN="" ZoneId="" ZoneKey="">
    <InventoryStatusTransitions>
        <InventoryStatusTransition InventoryStatus=""
            InventoryStatusTransitionKey="" NewInventoryStatus="" ZoneId=""/>
    </InventoryStatusTransitions>
    <ZoneEnterprises>
        <ZoneEnterprise EnterpriseCode="" ZoneEnterpriseKey="" ZoneKey="">
            <StorageConstraints>
                <StorageConstraint ItemClassification1=""
                    ItemClassification2="" ItemClassification3=""
                    StorageConstraintKey="" ZoneEnterpriseKey=""/>
            </StorageConstraints>
        </ZoneEnterprise>
    </ZoneEnterprises>
    <ZoneLocations>
        <ZoneLocation AisleNumber="" AisleSuffix="" BayNumber=""
            FreezeMoveIn="" FreezeMoveOut="" InStagingLocationId=""
            LevelNumber="" LocationBarCode="" LocationId=""
            LocationKey="" LocationSizeCode="" LocationType=""
            MoveInSeqNo="" MoveOutSeqNo="" OutStagingLocationId=""
            StorageCode="" VelocityCode="" ZoneId="">
            <LocationSize Description="" DimensionUom="" Height=""
                IsInfiniteCapacity="" Length="" LocationSizeCode=""
                LocationSizeKey="" MaxWeight="" TotalNumberOfRecords=""
                Volume="" VolumeUom="" WeightUom="" Width="">
                <LocationCapacities>
                    <LocationCapacity EnterpriseCode=""
                        ItemClassificationCode="" LocationCapacityKey=""
                        LocationSizeCode="" NoOfPackages="" PackagingType=""/>
                </LocationCapacities>
            </LocationSize>
            <SKUDedications>
                <SKUDedication EnterpriseCode="" ItemId="" LocationId=""
                    MaxQty="" MaxQuantity="" MinQty="" MinQuantity=""
                    ProductClass="" SKUDedicationKey="" Segment=""
                    SegmentType="" UnitOfMeasure=""/>
            </SKUDedications>
        </ZoneLocation>
    </ZoneLocations>
</Zone>
