{
  "OrderApproval": [
    {
      "ApprovalCycle": "",
      "ApprovalGroupKey": "",
      "ApproverComments": "",
      "ApproverUserID": "",
      "DelegateUserID": "",
      "IsForCurrentUser": "",
      "IsMandatory": "",
      "OrderApprovalDetails": {
        "OrderApprovalDetail": [
          {
            "ApprovalRuleID": "",
            "Message": "",
            "MessageCode": "",
            "OrderApprovalDetailKey": "",
            "OrderApprovalKey": "",
            "OrderHeaderKey": "",
            "OrderLine": {
              "BundleParentLine": {
                "OrderLineKey": "",
                "PrimeLineNo": "",
                "SubLineNo": ""
              },
              "OrderLineKey": ""
            },
            "OrderLineKey": ""
          }
        ],
        "TotalNumberOfRecords": ""
      },
      "OrderApprovalKey": "",
      "OrderHeaderKey": "",
      "PredecessorOrderApprSeq": "",
      "PredecessorOrderApprovals": {
        "OrderApproval": {
          "OrderApprovalKey": "",
          "Sequence": ""
        },
        "TotalNumberOfRecords": ""
      },
      "Sequence": "",
      "Status": "",
      "TeamCode": "",
      "UserGroupID": "",
      "UserID": ""
    }
  ],
  "TotalNumberOfRecords": ""
}