{
  "AllocationRuleID": "",
  "AuthorizationExpirationDate": "",
  "AutoCancelDate": "",
  "BillToID": "",
  "BuyerOrganizationCode": "",
  "CarrierAccountNo": "",
  "CarrierServiceCode": "",
  "ChargeActualFreightFlag": "",
  "ChargeTransactionDetails": {
    "ChargeTransactionDetail": [
      {
        "AuditTransactionID": "",
        "AuthorizationExpirationDate": "",
        "AuthorizationID": "",
        "BookAmount": "",
        "ChargeTransactionKey": "",
        "ChargeType": "",
        "CollectionDate": "",
        "CreditAmount": "",
        "CreditCardTransactions": {
          "CreditCardTransaction": [
            {
              "AuthAmount": "",
              "AuthAvs": "",
              "AuthCode": "",
              "AuthReturnCode": "",
              "AuthReturnFlag": "",
              "AuthReturnMessage": "",
              "AuthTime": "",
              "ChargeTransactionKey": "",
              "CreditCardTransactionKey": "",
              "InternalReturnCode": "",
              "InternalReturnFlag": "",
              "InternalReturnMessage": "",
              "ParentKey": "",
              "Reference1": "",
              "Reference2": "",
              "RequestId": "",
              "TranAmount": "",
              "TranRequestTime": "",
              "TranReturnCode": "",
              "TranReturnFlag": "",
              "TranReturnMessage": "",
              "TranType": ""
            }
          ]
        },
        "DebitAmount": "",
        "DistributedAmount": "",
        "HoldAgainstBook": "",
        "OpenAuthorizedAmount": "",
        "OrderHeaderKey": "",
        "OrderInvoiceKey": "",
        "PaymentKey": "",
        "PaymentMethod": {
          "AwaitingAuthInterfaceAmount": "",
          "AwaitingChargeInterfaceAmount": "",
          "ChargeSequence": "",
          "CheckNo": "",
          "CheckReference": "",
          "CreditCardExpDate": "",
          "CreditCardName": "",
          "CreditCardNo": "",
          "CreditCardType": "",
          "CustomerAccountNo": "",
          "CustomerPONo": "",
          "DisplayCreditCardNo": "",
          "IncompletePaymentType": "",
          "MaxChargeLimit": "",
          "PaymentKey": "",
          "PaymentReference1": "",
          "PaymentReference2": "",
          "PaymentReference3": "",
          "PaymentType": "",
          "RequestedAuthAmount": "",
          "RequestedChargeAmount": "",
          "SuspendAnyMoreCharges": "",
          "TotalAuthorized": "",
          "TotalCharged": "",
          "TotalRefundedAmount": "",
          "UnlimitedCharges": ""
        },
        "RequestAmount": "",
        "SettledAmount": "",
        "Status": "",
        "StatusReason": "",
        "TransactionDate": "",
        "UserExitStatus": ""
      }
    ],
    "TotalCredits": "",
    "TotalDebits": "",
    "TotalOpenAuthorizations": "",
    "TotalOpenBookings": ""
  },
  "CustomerEMailID": "",
  "CustomerPONo": "",
  "DeliveryCode": "",
  "Division": "",
  "DocumentType": "",
  "DraftOrderFlag": "",
  "EnteredBy": "",
  "EnterpriseCode": "",
  "EntryType": "",
  "FreightTerms": "",
  "HoldFlag": "",
  "HoldReasonCode": "",
  "MaxOrderStatus": "",
  "MaxOrderStatusDesc": "",
  "MinOrderStatus": "",
  "MinOrderStatusDesc": "",
  "NotificationReference": "",
  "NotificationType": "",
  "NotifyAfterShipmentFlag": "",
  "OrderDate": "",
  "OrderHeaderKey": "Required",
  "OrderLines": {
    "NumberOfOrderLines": "",
    "OrderLine": [
      {
        "AllocationDate": "",
        "CarrierAccountNo": "",
        "CarrierServiceCode": "",
        "CustomerLinePONo": "",
        "CustomerPONo": "",
        "DeliveryCode": "",
        "DepartmentCode": "",
        "FreightTerms": "",
        "HoldFlag": "",
        "HoldReasonCode": "",
        "ImportLicenseExpDate": "",
        "ImportLicenseNo": "",
        "InvoicedQty": "",
        "IsFirmPredefinedNode": "",
        "Item": {
          "CostCurrency": "",
          "CountryOfOrigin": "",
          "CustomerItem": "",
          "CustomerItemDesc": "",
          "ECCNNo": "",
          "HarmonizedCode": "",
          "ISBN": "",
          "ItemDesc": "",
          "ItemID": "",
          "ItemShortDesc": "",
          "ItemWeight": "",
          "ItemWeightUOM": "",
          "ManufacturerItem": "",
          "ManufacturerItemDesc": "",
          "ManufacturerName": "",
          "NMFCClass": "",
          "NMFCCode": "",
          "NMFCDescription": "",
          "ProductClass": "",
          "ProductLine": "",
          "ScheduleBCode": "",
          "SupplierItem": "",
          "SupplierItemDesc": "",
          "TaxProductCode": "",
          "UPCCode": "",
          "UnitCost": "",
          "UnitOfMeasure": ""
        },
        "KitCode": "",
        "LineSeqNo": "",
        "LineType": "",
        "MaxLineStatus": "",
        "MaxLineStatusDesc": "",
        "MinLineStatus": "",
        "MinLineStatusDesc": "",
        "OpenQty": "",
        "OrderHeaderKey": "",
        "OrderLineKey": "Required",
        "OrderedQty": "",
        "OrigOrderLineKey": "",
        "OriginalOrderedQty": "",
        "OtherCharges": "",
        "PackListType": "",
        "PersonInfoShipTo": {
          "AddressLine1": "",
          "AddressLine2": "",
          "AddressLine3": "",
          "AddressLine4": "",
          "AddressLine5": "",
          "AddressLine6": "",
          "AlternateEmailID": "",
          "Beeper": "",
          "City": "",
          "Company": "",
          "Country": "",
          "DayFaxNo": "",
          "DayPhone": "",
          "Department": "",
          "EMailID": "",
          "EveningFaxNo": "",
          "EveningPhone": "",
          "FirstName": "",
          "JobTitle": "",
          "LastName": "",
          "MiddleName": "",
          "MobilePhone": "",
          "OtherPhone": "",
          "PersonID": "",
          "PersonInfoKey": "",
          "State": "",
          "Suffix": "",
          "Title": "",
          "ZipCode": ""
        },
        "PersonalizeCode": "",
        "PersonalizeFlag": "",
        "PickableFlag": "",
        "PrimeLineNo": "",
        "Purpose": "",
        "ReceivingNode": "",
        "RemainingQty": "",
        "ReqCancelDate": "",
        "ReqDeliveryDate": "",
        "ReqShipDate": "",
        "ReservationID": "",
        "ReservationMandatory": "",
        "ReservationPool": "",
        "SCAC": "",
        "ScacAndService": "",
        "ScacAndServiceKey": "",
        "ShipNode": "",
        "ShipToID": "",
        "ShipTogetherNo": "",
        "SplitQty": "",
        "Status": "",
        "StatusQuantity": "",
        "SubLineNo": "",
        "isHistory": ""
      }
    ]
  },
  "OrderName": "",
  "OrderNo": "",
  "OrderType": "",
  "OriginalTax": "",
  "OriginalTotalAmount": "",
  "OtherCharges": "",
  "PaymentMethods": {
    "PaymentMethod": [
      {
        "AwaitingAuthInterfaceAmount": "",
        "AwaitingChargeInterfaceAmount": "",
        "ChargeSequence": "",
        "CheckNo": "",
        "CheckReference": "",
        "CreditCardExpDate": "",
        "CreditCardName": "",
        "CreditCardNo": "",
        "CreditCardType": "",
        "CustomerAccountNo": "",
        "CustomerPONo": "",
        "DisplayCreditCardNo": "",
        "IncompletePaymentType": "",
        "MaxChargeLimit": "",
        "PaymentKey": "",
        "PaymentReference1": "",
        "PaymentReference2": "",
        "PaymentReference3": "",
        "PaymentType": "",
        "RequestedAuthAmount": "",
        "RequestedChargeAmount": "",
        "SuspendAnyMoreCharges": "",
        "TotalAuthorized": "",
        "TotalCharged": "",
        "TotalRefundedAmount": "",
        "UnlimitedCharges": ""
      }
    ]
  },
  "PaymentStatus": "",
  "PersonInfoBillTo": {
    "AddressLine1": "",
    "AddressLine2": "",
    "AddressLine3": "",
    "AddressLine4": "",
    "AddressLine5": "",
    "AddressLine6": "",
    "AlternateEmailID": "",
    "Beeper": "",
    "City": "",
    "Company": "",
    "Country": "",
    "DayFaxNo": "",
    "DayPhone": "",
    "Department": "",
    "EMailID": "",
    "EveningFaxNo": "",
    "EveningPhone": "",
    "FirstName": "",
    "JobTitle": "",
    "LastName": "",
    "MiddleName": "",
    "MobilePhone": "",
    "OtherPhone": "",
    "PersonID": "",
    "PersonInfoKey": "",
    "State": "",
    "Suffix": "",
    "Title": "",
    "ZipCode": ""
  },
  "PersonInfoShipTo": {
    "AddressLine1": "",
    "AddressLine2": "",
    "AddressLine3": "",
    "AddressLine4": "",
    "AddressLine5": "",
    "AddressLine6": "",
    "AlternateEmailID": "",
    "Beeper": "",
    "City": "",
    "Company": "",
    "Country": "",
    "DayFaxNo": "",
    "DayPhone": "",
    "Department": "",
    "EMailID": "",
    "EveningFaxNo": "",
    "EveningPhone": "",
    "FirstName": "",
    "JobTitle": "",
    "LastName": "",
    "MiddleName": "",
    "MobilePhone": "",
    "OtherPhone": "",
    "PersonID": "",
    "PersonInfoKey": "",
    "State": "",
    "Suffix": "",
    "Title": "",
    "ZipCode": ""
  },
  "PersonalizeCode": "",
  "PriceProgramKey": "",
  "PriorityCode": "",
  "PriorityNumber": "",
  "Purpose": "",
  "ReceivingNode": "",
  "ReqCancelDate": "",
  "ReqDeliveryDate": "",
  "ReqShipDate": "",
  "SCAC": "",
  "ScacAndService": "",
  "ScacAndServiceKey": "",
  "SearchCriteria1": "",
  "SearchCriteria2": "",
  "SellerOrganizationCode": "",
  "ShipCompleteFlag": "",
  "ShipToID": "",
  "SourceIPAddress": "",
  "Status": "",
  "TaxExemptFlag": "",
  "TaxExemptionCertificate": "",
  "TaxJurisdiction": "",
  "TaxPayerId": "",
  "TermsCode": "",
  "TotalAdjustmentAmount": "",
  "isHistory": ""
}