{
  "Active": "",
  "AdapterKey": "",
  "AltImage": "",
  "AltImageBinding": "",
  "ApiName": "",
  "ApplicationCode": "",
  "ApplicationName": "",
  "BehaviorClassName": "",
  "Binding": "",
  "CanAddToMenu": "",
  "CloseWindowOnComplete": "",
  "DisplayBinding": "",
  "DocumentType": "",
  "EntityKeyName": "",
  "EventComponent": "",
  "FlowName": "",
  "FormClassName": "",
  "Height": "",
  "HelpApplicationCode": "",
  "HideMaxRecords": "",
  "HideNavigationPanel": "",
  "IgnoreDefaultApi": "",
  "IgnoreException": "",
  "Image": "",
  "Input": "",
  "InputNamespace": "",
  "IsPermissionControlled": "",
  "IsReadOnly": "",
  "Javascript": "",
  "Jsp": "",
  "OrigResourceId": "",
  "OutputNamespace": "",
  "OutputXmlTemplateFileName": "",
  "OutputXslTemplateFileName": "",
  "OverrideEntityId": "",
  "OverrideEntityKeyName": "",
  "OverrideFormClassName": "",
  "Parameter1": "",
  "Parameter2": "",
  "Parameter3": "",
  "Parameter4": "",
  "Parameter5": "",
  "ParentResourceId": "",
  "Popup": "",
  "ProtocolKey": "",
  "Redirector": "",
  "ResourceCreateType": "",
  "ResourceDesc": "",
  "ResourceId": "",
  "ResourceKey": "",
  "ResourcePermissionList": {
    "ResourcePermission": [
      {
        "ActivateFlag": "",
        "ReadOnlyFlag": "",
        "ResourceKey": "",
        "ResourcePermissionKey": "",
        "UsergroupKey": ""
      }
    ]
  },
  "ResourceSeq": "",
  "ResourceSubType": "",
  "ResourceType": "",
  "RollbackOnlyMode": "",
  "SelectionKeyName": "",
  "ServiceKey": "",
  "ShowDetail": "",
  "SkipAutoExecute": "",
  "SubResource": {
    "Resource": {
      "Active": "",
      "AdapterKey": "",
      "AltImage": "",
      "AltImageBinding": "",
      "ApiName": "",
      "ApplicationCode": "",
      "ApplicationName": "",
      "BehaviorClassName": "",
      "Binding": "",
      "CanAddToMenu": "",
      "CloseWindowOnComplete": "",
      "DisplayBinding": "",
      "DocumentType": "",
      "EntityKeyName": "",
      "EventComponent": "",
      "FlowName": "",
      "FormClassName": "",
      "Height": "",
      "HelpApplicationCode": "",
      "HideMaxRecords": "",
      "HideNavigationPanel": "",
      "IgnoreDefaultApi": "",
      "IgnoreException": "",
      "Image": "",
      "Input": "",
      "InputNamespace": "",
      "IsPermissionControlled": "",
      "IsReadOnly": "",
      "Javascript": "",
      "Jsp": "",
      "OrigResourceId": "",
      "OutputNamespace": "",
      "OutputXmlTemplateFileName": "",
      "OutputXslTemplateFileName": "",
      "OverrideEntityId": "",
      "OverrideEntityKeyName": "",
      "OverrideFormClassName": "",
      "Parameter1": "",
      "Parameter2": "",
      "Parameter3": "",
      "Parameter4": "",
      "Parameter5": "",
      "ParentResourceId": "",
      "Popup": "",
      "ProtocolKey": "",
      "Redirector": "",
      "ResourceCreateType": "",
      "ResourceDesc": "",
      "ResourceId": "",
      "ResourceKey": "",
      "ResourcePermissionList": {
        "ResourcePermission": [
          {
            "ActivateFlag": "",
            "ReadOnlyFlag": "",
            "ResourceKey": "",
            "ResourcePermissionKey": "",
            "Rights": "",
            "UserKey": "",
            "UsergroupKey": ""
          }
        ]
      },
      "ResourceSeq": "",
      "ResourceSubType": "",
      "ResourceType": "",
      "RollbackOnlyMode": "",
      "SelectionKeyName": "",
      "ServiceKey": "",
      "ShowDetail": "",
      "SkipAutoExecute": "",
      "SupportsSearchToDetail": "",
      "SuppressDecoration": "",
      "SystemKey": "",
      "Template": "",
      "ToolTip": "",
      "Url": "",
      "Version": "",
      "ViewGroupId": "",
      "ViewId": "",
      "Width": ""
    }
  },
  "SupportsSearchToDetail": "",
  "SuppressDecoration": "",
  "SystemKey": "",
  "Template": "",
  "ToolTip": "",
  "Url": "",
  "Version": "",
  "ViewGroupId": "",
  "ViewId": "",
  "Width": ""
}