{
  "BuyerMarkForNodeId": "",
  "BuyerOrganizationCode": "",
  "BuyerReceivingNodeId": "",
  "CarrierServiceCode": "",
  "Currency": "",
  "CustReqShipDate": "",
  "CustomerPoNo": "",
  "DeliveryCode": "",
  "DepartmentCode": "",
  "DoNotConsolidate": "",
  "DocumentType": "",
  "EnterpriseCode": "Required",
  "ExternalReleaseIdentifier": "",
  "FOB": "",
  "FromAddress": {
    "AddressLine1": "",
    "AddressLine2": "",
    "AddressLine3": "",
    "AddressLine4": "",
    "AddressLine5": "",
    "AddressLine6": "",
    "AlternateEmailID": "",
    "Beeper": "",
    "City": "",
    "Company": "",
    "Country": "",
    "DayFaxNo": "",
    "DayPhone": "",
    "Department": "",
    "EMailID": "",
    "ErrorTxt": "",
    "EveningFaxNo": "",
    "EveningPhone": "",
    "FirstName": "",
    "HttpUrl": "",
    "IsCommercialAddress": "",
    "JobTitle": "",
    "LastName": "",
    "MiddleName": "",
    "MobilePhone": "",
    "OtherPhone": "",
    "PersonID": "",
    "PersonInfoKey": "",
    "PreferredShipAddress": "",
    "State": "",
    "Suffix": "",
    "TaxGeoCode": "",
    "Title": "",
    "UseCount": "",
    "VerificationStatus": "",
    "ZipCode": ""
  },
  "GiftFlag": "",
  "Instructions": {
    "Instruction": [
      {
        "InstructionDetailKey": "",
        "InstructionText": "",
        "InstructionType": "",
        "InstructionURL": "",
        "InstructionUsage": "",
        "ReferenceKey": "",
        "SequenceNo": "",
        "TableName": ""
      }
    ]
  },
  "ItemClassification": "",
  "LevelOfService": "",
  "MarkForAddress": {
    "AddressLine1": "",
    "AddressLine2": "",
    "AddressLine3": "",
    "AddressLine4": "",
    "AddressLine5": "",
    "AddressLine6": "",
    "AlternateEmailID": "",
    "Beeper": "",
    "City": "",
    "Company": "",
    "Country": "",
    "DayFaxNo": "",
    "DayPhone": "",
    "Department": "",
    "EMailID": "",
    "ErrorTxt": "",
    "EveningFaxNo": "",
    "EveningPhone": "",
    "FirstName": "",
    "HttpUrl": "",
    "IsCommercialAddress": "",
    "JobTitle": "",
    "LastName": "",
    "MiddleName": "",
    "MobilePhone": "",
    "OtherPhone": "",
    "PersonID": "",
    "PersonInfoKey": "",
    "PreferredShipAddress": "",
    "State": "",
    "Suffix": "",
    "TaxGeoCode": "",
    "Title": "",
    "UseCount": "",
    "VerificationStatus": "",
    "ZipCode": ""
  },
  "OrderAvailableOnSystem": "",
  "OrderHeaderKey": "",
  "OrderLines": {
    "OrderLine": [
      {
        "CustomerPONo": "",
        "DepartmentCode": "",
        "Instructions": {
          "Instruction": [
            {
              "InstructionDetailKey": "",
              "InstructionText": "",
              "InstructionType": "",
              "InstructionURL": "",
              "InstructionUsage": "",
              "ReferenceKey": "",
              "SequenceNo": "",
              "TableName": ""
            }
          ]
        },
        "Item": {
          "CountryOfOrigin": "",
          "ItemDesc": "",
          "ItemID": "Required",
          "ProductClass": "",
          "UnitOfMeasure": ""
        },
        "KitCode": "",
        "OrderLineInvAttRequest": {
          "BatchNo": "",
          "LotAttribute1": "",
          "LotAttribute2": "",
          "LotAttribute3": "",
          "LotKeyReference": "",
          "LotNumber": "",
          "ManufacturingDate": "",
          "RevisionNo": ""
        },
        "OrderedQty": "Required",
        "PersonInfoMarkFor": {
          "AddressLine1": "",
          "AddressLine2": "",
          "AddressLine3": "",
          "AddressLine4": "",
          "AddressLine5": "",
          "AddressLine6": "",
          "AlternateEmailID": "",
          "Beeper": "",
          "City": "",
          "Company": "",
          "Country": "",
          "DayFaxNo": "",
          "DayPhone": "",
          "Department": "",
          "EMailID": "",
          "ErrorTxt": "",
          "EveningFaxNo": "",
          "EveningPhone": "",
          "FirstName": "",
          "HttpUrl": "",
          "IsCommercialAddress": "",
          "JobTitle": "",
          "LastName": "",
          "MiddleName": "",
          "MobilePhone": "",
          "OtherPhone": "",
          "PersonID": "",
          "PersonInfoKey": "",
          "PreferredShipAddress": "",
          "State": "",
          "Suffix": "",
          "TaxGeoCode": "",
          "Title": "",
          "UseCount": "",
          "VerificationStatus": "",
          "ZipCode": ""
        },
        "PrimeLineNo": "",
        "Segment": "",
        "SegmentType": "",
        "SerialNo": "",
        "SubLineNo": ""
      }
    ]
  },
  "OrderNo": "",
  "OrderReleaseKey": "",
  "OrderType": "",
  "PackAndHold": "",
  "PacklistType": "",
  "PriorityCode": "",
  "ReceivingNode": "",
  "ReleaseNo": "",
  "ReqCancelDate": "",
  "ReqDeliveryDate": "",
  "ReqShipDate": "",
  "SCAC": "",
  "SellerOrganizationCode": "",
  "ShipNode": "",
  "ShipmentConsolidationGroupId": "",
  "ShipmentKey": "",
  "ShipmentNo": "",
  "SpecialServices": {
    "SpecialService": [
      {
        "SpecialServicesCode": ""
      }
    ]
  },
  "ToAddress": {
    "AddressLine1": "",
    "AddressLine2": "",
    "AddressLine3": "",
    "AddressLine4": "",
    "AddressLine5": "",
    "AddressLine6": "",
    "AlternateEmailID": "",
    "Beeper": "",
    "City": "",
    "Company": "",
    "Country": "",
    "DayFaxNo": "",
    "DayPhone": "",
    "Department": "",
    "EMailID": "",
    "ErrorTxt": "",
    "EveningFaxNo": "",
    "EveningPhone": "",
    "FirstName": "",
    "HttpUrl": "",
    "IsCommercialAddress": "",
    "JobTitle": "",
    "LastName": "",
    "MiddleName": "",
    "MobilePhone": "",
    "OtherPhone": "",
    "PersonID": "",
    "PersonInfoKey": "",
    "PreferredShipAddress": "",
    "State": "",
    "Suffix": "",
    "TaxGeoCode": "",
    "Title": "",
    "UseCount": "",
    "VerificationStatus": "",
    "ZipCode": ""
  }
}