{
  "Action": "Create",
  "DeliveryPlanClosedFlag": "",
  "DeliveryPlanDate": "",
  "DeliveryPlanKey": "",
  "DeliveryPlanName": "",
  "DeliveryPlanNo": "",
  "DeliveryPlanPlannedFlag": "",
  "DocumentType": "",
  "EnterpriseCode": "",
  "OverrideModificationRules": "Y",
  "OwnerOrganizationCode": "",
  "RemoveContentOnDelete": "Y",
  "Shipments": {
    "Shipment": [
      {
        "AssociationAction": "Add",
        "SellerOrganizationCode": "",
        "ShipNode": "",
        "ShipmentKey": "",
        "ShipmentNo": ""
      }
    ]
  }
}