{
  "ActualFreightCharge": "",
  "ActualWeight": "",
  "ActualWeightUOM": "",
  "AppliedWeight": "",
  "AppliedWeightUOM": "",
  "CODReturnTrackingNo": "",
  "ContainerNo": "",
  "ContainerScm": "",
  "IsPackProcessComplete": "",
  "Load": {
    "LoadNo": ""
  },
  "LoadKey": "",
  "LocationId": "",
  "Manifest": {
    "ManifestDate": ""
  },
  "ManifestKey": "",
  "ManifestNo": "",
  "PrinterPreference": {
    "PrinterId": "",
    "UserId": "",
    "UsergroupId": "",
    "WorkStationId": ""
  },
  "SCAC": "",
  "ShipNode": "",
  "Shipment": {
    "SellerOrganizationCode": "",
    "ShipNode": "",
    "ShipmentNo": ""
  },
  "ShipmentContainerKey": "",
  "ShipmentKey": "",
  "SpecialServicesSurcharge": "",
  "TrackingNo": ""
}