{
  "AvailableTag": "",
  "BatchNo": "",
  "InventoryItem": {
    "InventoryItemKey": "",
    "ItemID": "",
    "OrganizationCode": "Required",
    "ProductClass": "",
    "UnitOfMeasure": ""
  },
  "InventoryItemKey": "",
  "InventoryTagKey": "",
  "LotAttribute1": "",
  "LotAttribute2": "",
  "LotAttribute3": "",
  "LotKeyReference": "",
  "LotNumber": "",
  "ManufacturingDate": "",
  "MaximumRecords": "",
  "RevisionNo": "",
  "TotalDemand": "",
  "TotalOnhandSupply": "",
  "TotalOtherSupply": ""
}