{
  "Constraints": {
    "CannotScheduleAfterConstraints": {
      "Constraint": {
        "ConstrainingDate": "",
        "ConstrainingOrderLineKey": "",
        "ConstraintDate": "",
        "ConstraintReason": "",
        "OrderLine": {
          "Item": {
            "ItemDesc": "",
            "ItemID": "",
            "UnitOfMeasure": ""
          },
          "ItemGroupCode": "",
          "OrderLineKey": "",
          "PrimeLineNo": "",
          "SubLineNo": ""
        }
      }
    },
    "CannotScheduleBeforeConstraints": {
      "Constraint": {
        "ConstrainingDate": "",
        "ConstrainingOrderLineKey": "",
        "ConstraintDate": "",
        "ConstraintReason": "",
        "OrderLine": {
          "Item": {
            "ItemDesc": "",
            "ItemID": "",
            "UnitOfMeasure": ""
          },
          "ItemGroupCode": "",
          "OrderLineKey": "",
          "PrimeLineNo": "",
          "SubLineNo": ""
        }
      }
    },
    "CannotScheduleConstraints": {
      "Constraint": {
        "ConstrainingDate": "",
        "ConstrainingOrderLineKey": "",
        "ConstraintDate": "",
        "ConstraintReason": "",
        "OrderLine": {
          "Item": {
            "ItemDesc": "",
            "ItemID": "",
            "UnitOfMeasure": ""
          },
          "ItemGroupCode": "",
          "OrderLineKey": "",
          "PrimeLineNo": "",
          "SubLineNo": ""
        }
      }
    }
  },
  "DocumentType": "",
  "EnterpriseCode": "",
  "Item": {
    "ItemDesc": "",
    "ItemID": "",
    "UnitOfMeasure": ""
  },
  "OrderHeaderKey": "",
  "OrderLineKey": "",
  "OrderNo": "",
  "PrimeLineNo": "",
  "SubLineNo": ""
}