{
  "BatchNo": "",
  "FoundTags": {
    "Tag": {
      "BatchNo": "",
      "InventoryItem": {
        "InventoryItemKey": "",
        "InventoryOrganizationCode": "",
        "ItemID": "",
        "ProductClass": "",
        "UnitOfMeasure": ""
      },
      "InventoryItemKey": "",
      "InventoryTagKey": "",
      "LotAttribute1": "",
      "LotAttribute2": "",
      "LotAttribute3": "",
      "LotKeyReference": "",
      "LotNumber": "",
      "ManufacturingDate": "",
      "RevisionNo": ""
    },
    "TotalNumberOfRecords": ""
  },
  "InventoryItem": {
    "ItemID": "",
    "OrganizationCode": "Required",
    "ProductClass": "",
    "UnitOfMeasure": ""
  },
  "LotAttribute1": "",
  "LotAttribute2": "",
  "LotAttribute3": "",
  "LotKeyReference": "",
  "LotNumber": "",
  "ManufacturingDate": "",
  "MaximumRecords": "",
  "RevisionNo": ""
}