<?xml version="1.0" encoding="UTF-8"?>
<DockAppointment AppointmentNo="" AppointmentType="" BolNo="" Carrier=""
    DockAppointmentKey="" LoadKey="" LocationId="" Node=""
    OrderHeaderKey="" OrganizationCode="" ProNo=""
    ResPoolConsmptnDtlsKey="" ShipmentKey="" TrailerNo="" xmlns="http://www.sterlingcommerce.com/documentation/WMS/MANAGE_DOCK_APPOINTMENT/ON_SUCCESS">
    <yfc:doc>
        <Attributes>
            <Attribute DataType="String" Name="LocationId"/>
        </Attributes>
    </yfc:doc>
    <ResourcePoolCapacityConsumptionDetails ReservationId="">
        <CapacityConsumption ConsumptionDate="" EndTime="" StartTime=""/>
    </ResourcePoolCapacityConsumptionDetails>
</DockAppointment>
