https://digitalecom.atlassian.net/browse/IESSF-578

EP3515BEJBAA002JA000021  
IIB
for the 2nd payload: 06 Jul 2024 03:52:47:896
<InventorySnapShot InventoryFeedType="1" StatusDate="2024-07-06" OrganizationCode="TITAN_GCC"><ShipNode ShipNode="XDF"><Item ItemID="EP3515BEJBAA00" LotNumber="2JA000021" CFAProductCode="71" ProductCode="B"><SupplyDetails Quantity="1"/></Item></ShipNode></InventorySnapShot>


in OMS - 2024-07-06 04:05:21.0
12 days ago - 2024-07-06 13:35:20.894 GMT+5:30 - mulesoft - 83cc0c1992831601b9aca7393fReplica krftr
Plain Text
$[MuleRuntime].uber.18479: [ibd-jewelry-order-create-papi].post:\inventory\reservation:application\json:ibd-jewelry-order-create-config.BLOCKING @75cab5bc - {
  "correlationId" : "83cc0c1992831601b9aca7393f",
  "message" : "START of inventory reservation flow",
  "tracePoint" : "START",
  "priority" : "INFO",
  "category" : "com.titan.mulesoft",
  "elapsed" : 0,
  "locationInfo" : {
    "lineInFile" : "108",
    "component" : "json-logger:logger",
    "fileName" : "ibd-jewellery-order-create-papi.xml",
    "rootContainer" : "post:\\inventory\\reservation:application\\json:ibd-jewelry-order-create-config"
  },
  "timestamp" : "2024-07-06T08:05:20.893Z",
  "content" : {
    "eventContext" : {
      "businessId" : "JEWELRY-ORDER-CREATE-PAPI01",
      "source" : "sfcc",
      "target" : "SFCC",
      "inboundUri" : "/api/v1/inventory/reservation",
      "method" : "POST"
    },
    "requestDetails" : {
      "reservationId" : "7c30255fce0f3c084ee70dc982",
      "itemDetails" : [ {
        "itemId" : "EP3515BEJBAA002JA000021",
        "requiredQty" : "1"
      } ]
    }
  },
  "applicationName" : "jewelry-order-create-papi-app",
  "applicationVersion" : "1.0.89",
  "environment" : "prod",
  "threadName" : "[MuleRuntime].uber.18479: [ibd-jewelry-order-create-papi].post:\\inventory\\reservation:application\\json:ibd-jewelry-order-create-config.BLOCKING @75cab5bc"
}
12 days ago - 2024-07-06 13:35:21.206 GMT+5:30 - mulesoft - 83cc0c1992831601b9aca7393fReplica krftr
Plain Text
$[MuleRuntime].uber.18480: [ibd-jewelry-order-create-papi].post:\inventory\reservation:application\json:ibd-jewelry-order-create-config.BLOCKING @75cab5bc - {
  "correlationId" : "83cc0c1992831601b9aca7393f",
  "message" : "END of inventory registration flow",
  "tracePoint" : "END",
  "priority" : "INFO",
  "category" : "com.titan.mulesoft",
  "elapsed" : 313,
  "locationInfo" : {
    "lineInFile" : "129",
    "component" : "json-logger:logger",
    "fileName" : "ibd-jewellery-order-create-papi.xml",
    "rootContainer" : "post:\\inventory\\reservation:application\\json:ibd-jewelry-order-create-config"
  },
  "timestamp" : "2024-07-06T08:05:21.206Z",
  "content" : {
    "eventContext" : {
      "businessId" : "JEWELRY-ORDER-CREATE-PAPI01",
      "source" : "sfcc",
      "target" : "SFCC",
      "inboundUri" : "/api/v1/inventory/reservation",
      "method" : "POST"
    },
    "responseDetails" : [ {
      "reservationId" : "7c30255fce0f3c084ee70dc982",
      "itemId" : "EP3515BEJBAA002JA000021",
      "qtyToBeReserved" : "1.00",
      "totalReservedQty" : "1.00"
    } ]
  },
  "applicationName" : "jewelry-order-create-papi-app",
  "applicationVersion" : "1.0.89",
  "environment" : "prod",
  "threadName" : "[MuleRuntime].uber.18480: [ibd-jewelry-order-create-papi].post:\\inventory\\reservation:application\\json:ibd-jewelry-order-create-config.BLOCKING @75cab5bc"
}




12 days ago - 2024-07-06 13:39:37.255 GMT+5:30 - mulesoft - 20240706040935Replica jjnv7
Plain Text
$[MuleRuntime].uber.7231: [ibd-inventory-sterling-eapi].put:\inventory:application\xml:ibd-inventory-sterling-eapi-config.BLOCKING @3afd896c - {
  "correlationId" : "20240706040935",
  "message" : "START Update Inventory",
  "tracePoint" : "START",
  "priority" : "INFO",
  "category" : "com.titan.mulesoft",
  "elapsed" : 0,
  "locationInfo" : {
    "lineInFile" : "54",
    "component" : "json-logger:logger",
    "fileName" : "ibd-inventory-sterling-eapi.xml",
    "rootContainer" : "put:\\inventory:application\\xml:ibd-inventory-sterling-eapi-config"
  },
  "timestamp" : "2024-07-06T08:09:37.251Z",
  "content" : {
    "eventContext" : {
      "businessID" : "INV-EAPI01",
      "sourceChannel" : "SterlingOMS",
      "inboundURI" : "/api/v1/inventory",
      "method" : "PUT"
    },
    "payload" : "<?xml version='1.0' encoding='UTF-8'?><InventoryItem ItemID=\"EP3515BEJBAA002JA000021\" ProductClass=\"FQ\" UnitOfMeasure=\"EACH\"><Item ItemID=\"EP3515BEJBAA002JA000021\" UnitOfMeasure=\"EACH\"><PrimaryInformation ProductLine=\"JEWEL\"/><Extn ExtnBrandCode=\"TQ\"/></Item><AvailabilityChanges><AvailabilityChange AlertRaisedOn=\"2024-07-06T04:07:57-04:00\" FirstFutureAvailableDate=\"2500-01-01\" FutureAvailableDate=\"2500-01-01\" FutureAvailableQuantity=\"0.00\" Node=\"XDF\" OnhandAvailableDate=\"2500-01-01\" OnhandAvailableQuantity=\"0.00\"/></AvailabilityChanges></InventoryItem>"
  },
  "applicationName" : "inventory-sterling-eapi",
  "applicationVersion" : "1.0.19",
  "environment" : "prod",
  "threadName" : "[MuleRuntime].uber.7231: [ibd-inventory-sterling-eapi].put:\\inventory:application\\xml:ibd-inventory-sterling-eapi-config.BLOCKING @3afd896c"
}




17 days ago - 2024-07-06 13:39:51.087 GMT+5:30 - mulesoft - 781153811-1a4590b0-3b6f-11ef-bdf4-6ede215791c7Replica krftr
Plain Text
$[MuleRuntime].uber.18483: [ibd-jewelry-order-create-papi].publish-to-ibm-mq-and-ackUpdateFlow.BLOCKING @59e1c5b5 - {
  "correlationId" : "781153811-1a4590b0-3b6f-11ef-bdf4-6ede215791c7",
  "message" : "Update Order Status Request",
  "tracePoint" : "BEFORE_REQUEST",
  "priority" : "INFO",
  "category" : "com.titan.mulesoft",
  "elapsed" : 7081,
  "locationInfo" : {
    "lineInFile" : "164",
    "component" : "json-logger:logger",
    "fileName" : "system/sys-order-sfcc-api.xml",
    "rootContainer" : "update-order-status-request-sapi-flow"
  },
  "timestamp" : "2024-07-06T08:09:51.087Z",
  "content" : {
    "eventContext" : {
      "businessID" : "JEWELRY-ORDER-CREATE-PAPI01",
      "sourceChannel" : "SFCC",
      "targetChannel" : "OMS",
      "inboundURI" : "NA",
      "method" : "NA",
      "sfccRealm" : "tanishq_UAE"
    },
    "orderNo" : "00002105",
    "payload" : {
      "c_ACK_STATUS" : "EXPORTED_TO_QUEUE"
    }
  },
  "applicationName" : "jewelry-order-create-papi-app",
  "applicationVersion" : "1.0.89",
  "environment" : "prod",
  "threadName" : "[MuleRuntime].uber.18483: [ibd-jewelry-order-create-papi].publish-to-ibm-mq-and-ackUpdateFlow.BLOCKING @59e1c5b5"
}




